pttavm/__init__.py
pttavm/client.py
pttavm/py.typed
pttavm/models/barcode.py
pttavm/models/category.py
pttavm/models/product.py
pttavm/models/product_update.py
pttavm/models/stock.py
pttavm/models/validation_rules.py
pttavm/models/variant.py
pttavm/services/base_service.py
pttavm/services/category_service.py
pttavm/services/product_service.py
pttavm/services/stock_service.py
pttavm/services/version_service.py
pttavm/utils/archiver.py
pttavm/utils/version.py
pttavm_python-0.1.5.dist-info/METADATA
pttavm_python-0.1.5.dist-info/WHEEL
pttavm_python-0.1.5.dist-info/top_level.txt
pttavm_python-0.1.5.dist-info/RECORD
